MANIFEST.in
setup.py
gitwalker/__init__.py
gitwalker/git.py
gitwalker/main.py
gitwalker/tools.py
gitwalker/util.py
gitwalker.egg-info/PKG-INFO
gitwalker.egg-info/SOURCES.txt
gitwalker.egg-info/dependency_links.txt
gitwalker.egg-info/entry_points.txt
gitwalker.egg-info/requires.txt
gitwalker.egg-info/top_level.txt
gitwalker/bin/texcount.pl
scripts/gitwalk_plot