Metadata-Version: 1.0
Name: gitwalker
Version: 0.1.5
Summary: A tool for collecting data from git repositories.
Home-page: https://github.com/alexsparrow/gitwalker
Author: Alex Sparrow
Author-email: alspar@gmail.com
License: GPL
Platform: UNKNOWN
